wnix/__init__.py
wnix/__pycache__/__init__.cpython-310.pyc
wnix/bin/__init__.py
wnix/bin/cat.py
wnix/bin/grep.py
wnix/bin/man.py
wnix/bin/sort.py
wnix/bin/what.py
wnix/bin/__pycache__/__init__.cpython-310.pyc
wnix/bin/__pycache__/grep.cpython-310.pyc
wnix/bin/__pycache__/sort.cpython-310.pyc
wnix/bin/__pycache__/what.cpython-310.pyc
wnix/lib/__init__.py
wnix/lib/grep.py
wnix/lib/what.py
wnix/lib/__pycache__/__init__.cpython-310.pyc
wnix/lib/__pycache__/grep.cpython-310.pyc
wnix/lib/__pycache__/what.cpython-310.pyc
wnix-0.0.20.dist-info/METADATA
wnix-0.0.20.dist-info/WHEEL
wnix-0.0.20.dist-info/entry_points.txt
wnix-0.0.20.dist-info/top_level.txt
wnix-0.0.20.dist-info/RECORD
