Metadata-Version: 2.1
Name: wnix
Version: 0.0.20
Summary: Unix coreutils for software 2.0
Author-email: Jason Wilkes <notarealdeveloper@gmail.com>
Project-URL: source, https://github.com/notarealdeveloper/wnix
Requires-Dist: pytest
Requires-Dist: pandas
Requires-Dist: is-instance
Requires-Dist: assure
Requires-Dist: mmry >=0.0.5
Requires-Dist: embd >=0.1.4
Requires-Dist: kern >=0.0.11
